common/__init__.py
common/cli.py
common/constants.py
common/ini.py
common/udptools.py
common/utils.py
simonski_pycommon-0.0.5.dist-info/LICENSE.txt
simonski_pycommon-0.0.5.dist-info/METADATA
simonski_pycommon-0.0.5.dist-info/WHEEL
simonski_pycommon-0.0.5.dist-info/top_level.txt
simonski_pycommon-0.0.5.dist-info/RECORD
